AbdallahRadwanLib/__init__.py
AbdallahRadwanLib/arUtilityConfig.py
AbdallahRadwanLib/arUtilityConst.py
AbdallahRadwanLib/arUtilityDBOracle.py
AbdallahRadwanLib/arUtilityDBSqlAlchemy.py
AbdallahRadwanLib/arUtilityEncryption.py
AbdallahRadwanLib/arUtilityEnum.py
AbdallahRadwanLib/arUtilityFile.py
AbdallahRadwanLib/arUtilityGeneral.py
AbdallahRadwanLib/arUtilitySettings.py
AbdallahRadwanLib-1.5.dist-info/LICENSE.txt
AbdallahRadwanLib-1.5.dist-info/METADATA
AbdallahRadwanLib-1.5.dist-info/WHEEL
AbdallahRadwanLib-1.5.dist-info/top_level.txt
AbdallahRadwanLib-1.5.dist-info/RECORD
