Metadata-Version: 2.1
Name: AbdallahRadwanLib
Version: 1.5
Summary: My First Package for Python Projects with PyPI Package - October 2024
Home-page: https://github.com/abdorado1984/AbdallahPackage
Author: Abdallah Radwan
Author-email: AbdallahRadwan2011@gmail.com
License: MIT
Classifier: Programming Language :: Python :: 3
Classifier: Operating System :: OS Independent
Classifier: License :: OSI Approved :: MIT License
Requires-Python: >=3.12
License-File: LICENSE.txt
